elasticsearch_logger/__init__.py
elasticsearch_logger/_version.py
elasticsearch_logger/elasticsearch_logger.py
elasticsearch_logger-0.0.2.dist-info/LICENSE.txt
elasticsearch_logger-0.0.2.dist-info/METADATA
elasticsearch_logger-0.0.2.dist-info/WHEEL
elasticsearch_logger-0.0.2.dist-info/top_level.txt
elasticsearch_logger-0.0.2.dist-info/RECORD
