Metadata-Version: 2.1
Name: elasticsearch-logger
Version: 0.0.2
Summary: Library for logging to Elastic Search.
Home-page: https://github.com/mmedek/es-logger
Author: Michal Medek
Author-email: mmedek94@gmail.com
License: UNKNOWN
Keywords: logging,es,elastic search
Platform: any
License-File: LICENSE.txt
